hybrid_vul/__init__.py
hybrid_vul/__main__.py
hybrid_vul/cli.py
hybrid_vul/sav_gannt_c.py
hybrid_vul/mlp/__init__.py
hybrid_vul/mlp/make_features.py
hybrid_vul/mlp/train_cached.py
hybrid_vul-0.1.0.dist-info/METADATA
hybrid_vul-0.1.0.dist-info/WHEEL
hybrid_vul-0.1.0.dist-info/entry_points.txt
hybrid_vul-0.1.0.dist-info/top_level.txt
hybrid_vul-0.1.0.dist-info/RECORD
