Metadata-Version: 2.4
Name: hybrid-vul
Version: 0.1.0
Summary: Hybrid-Vul: cached features + MLP with timeline chart
Requires-Python: >=3.9
Requires-Dist: numpy>=1.24
Requires-Dist: pandas>=2.0
Requires-Dist: scikit-learn>=1.2
Requires-Dist: matplotlib>=3.8
